setup.py
percept/__init__.py
percept.egg-info/PKG-INFO
percept.egg-info/SOURCES.txt
percept.egg-info/dependency_links.txt
percept.egg-info/top_level.txt
percept/bin/__init__.py
percept/bin/percept-admin.py
percept/conf/__init__.py
percept/conf/base.py
percept/conf/global_settings.py
percept/datahandlers/__init__.py
percept/datahandlers/formatters.py
percept/datahandlers/inputs.py
percept/fields/__init__.py
percept/fields/base.py
percept/fields/caches.py
percept/management/__init__.py
percept/management/base.py
percept/management/commands.py
percept/project_template/config/__init__.py
percept/project_template/config/settings.py
percept/project_template/formatters/__init__.py
percept/project_template/inputs/__init__.py
percept/project_template/tasks/__init__.py
percept/project_template/tests/__init__.py
percept/project_template/tests/test_runner.py
percept/project_template/workflows/__init__.py
percept/tasks/__init__.py
percept/tasks/base.py
percept/tasks/preprocess.py
percept/tasks/train.py
percept/tasks/validate.py
percept/tests/__init__.py
percept/tests/framework.py
percept/tests/test_runner.py
percept/tests/test_settings.py
percept/tests/commands/__init__.py
percept/tests/commands/test.py
percept/utils/__init__.py
percept/utils/input.py
percept/utils/models.py
percept/utils/registry.py
percept/utils/workflow.py
percept/workflows/__init__.py
percept/workflows/base.py
percept/workflows/datastores.py
percept/workflows/runners.py
percept/workflows/commands/__init__.py
percept/workflows/commands/list_tasks.py
percept/workflows/commands/run_flow.py
percept/workflows/commands/shell.py
percept/workflows/commands/start_project.py