Metadata-Version: 1.0
Name: percept
Version: 0.14
Summary: Modular machine learning framework that is easy to test and deploy.
Home-page: https://github.com/equirio/percept
Author: Equirio
Author-email: vik@equirio.com
License: AGPL
Keywords: ml machine learning nlp ai algorithm
Platform: UNKNOWN
